docs/Makefile
docs/api_reference.rst
docs/conf.py
docs/contributing.rst
docs/history.rst
docs/index.rst
docs/make.bat
docs/readme.rst
docs/spharpy.rst
docs/modules/spharpy.beamforming.rst
docs/modules/spharpy.indexing.rst
docs/modules/spharpy.interpolate.rst
docs/modules/spharpy.plot.rst
docs/modules/spharpy.samplings.rst
docs/modules/spharpy.spatial.rst
docs/modules/spharpy.spherical.rst
docs/modules/spharpy.transforms.rst
examples/colormaps.py
spharpy/__init__.py
spharpy/_deprecation.py
spharpy/interpolate.py
spharpy/special.py
spharpy/spherical.py
spharpy/beamforming/__init__.py
spharpy/beamforming/beamforming.py
spharpy/indexing/__init__.py
spharpy/indexing/channel_indexing.py
spharpy/plot/__init__.py
spharpy/plot/cmap.py
spharpy/plot/spatial.py
spharpy/samplings/__init__.py
spharpy/samplings/coordinates.py
spharpy/samplings/helpers.py
spharpy/samplings/interior.py
spharpy/samplings/samplings.py
spharpy/samplings/_eqsp/__init__.py
spharpy/samplings/_eqsp/partitions.py
spharpy/spatial/__init__.py
spharpy/spatial/spatial.py
spharpy/transforms/__init__.py
spharpy/transforms/rotations.py
tests/__init__.py
tests/ballon_plot.py
tests/conftest.py
tests/test_acn_nm_indexing.py
tests/test_aperture.py
tests/test_beamforming.py
tests/test_coordinate_transforms.py
tests/test_coordinates.py
tests/test_eq_area_partitions.py
tests/test_indexing.py
tests/test_interpolate.py
tests/test_modal_strength.py
tests/test_plots.py
tests/test_rotations.py
tests/test_samplings.ipynb
tests/test_samplings.py
tests/test_samplings_interior.py
tests/test_special.py
tests/test_spharpy.py
tests/test_spherical_harmonics.py
tests/data/Y_diff_azi.csv
tests/data/Y_diff_real_azi.csv
tests/data/Y_grad_azi.csv
tests/data/Y_grad_ele.csv
tests/data/Y_grad_real_azi.csv
tests/data/Y_grad_real_ele.csv
tests/data/bessel.csv
tests/data/bessel_diff.csv
tests/data/dolph_cheby_mainlobe.csv
tests/data/dolph_cheby_sidelobe.csv
tests/data/hankel_1.csv
tests/data/hankel_1_diff.csv
tests/data/hankel_2.csv
spharpy-0.6.2.dist-info/LICENSE
spharpy-0.6.2.dist-info/METADATA
spharpy-0.6.2.dist-info/WHEEL
spharpy-0.6.2.dist-info/top_level.txt
spharpy-0.6.2.dist-info/RECORD
