Metadata-Version: 2.2
Name: spharpy
Version: 0.6.2
Summary: Project for data formats in acoustics.
Author-email: The pyfar developers <info@pyfar.org>
License: MIT License
Project-URL: Tracker, https://github.com/pyfar/spharpy/issues
Project-URL: Documentation, https://spharpy.readthedocs.io/
Project-URL: Download, https://pypi.org/project/spharpy/
Project-URL: Homepage, https://pyfar.org/
Project-URL: Source, https://github.com/pyfar/spharpy
Project-URL: Changelog, https://github.com/pyfar/spharpy/blob/main/HISTORY.rst
Keywords: acoustics,pyfar
Classifier: Development Status :: 4 - Beta
Classifier: Intended Audience :: Science/Research
Classifier: License :: OSI Approved :: MIT License
Classifier: Natural Language :: English
Classifier: Programming Language :: Python :: 3
Classifier: Programming Language :: Python :: 3.8
Classifier: Programming Language :: Python :: 3.9
Classifier: Programming Language :: Python :: 3.10
Classifier: Programming Language :: Python :: 3.11
Classifier: Programming Language :: Python :: 3.12
Classifier: Programming Language :: Python :: 3.13
Requires-Python: >=3.8
License-File: LICENSE
Requires-Dist: numpy>=1.22
Requires-Dist: scipy
Requires-Dist: urllib3
Requires-Dist: matplotlib>=3.3.0
Requires-Dist: pyfar<0.8.0
Requires-Dist: pytz
Provides-Extra: deploy
Requires-Dist: twine; extra == "deploy"
Requires-Dist: wheel; extra == "deploy"
Requires-Dist: build; extra == "deploy"
Requires-Dist: setuptools; extra == "deploy"
Requires-Dist: bump-my-version; extra == "deploy"
Provides-Extra: tests
Requires-Dist: pytest; extra == "tests"
Requires-Dist: pytest-cov; extra == "tests"
Requires-Dist: watchdog; extra == "tests"
Requires-Dist: ruff==0.8.3; extra == "tests"
Requires-Dist: coverage; extra == "tests"
Provides-Extra: docs
Requires-Dist: sphinx; extra == "docs"
Requires-Dist: autodocsumm>=0.2.14; extra == "docs"
Requires-Dist: pydata-sphinx-theme; extra == "docs"
Requires-Dist: sphinx_mdinclude; extra == "docs"
Requires-Dist: sphinx-design; extra == "docs"
Requires-Dist: sphinx-favicon; extra == "docs"
Requires-Dist: sphinx-reredirects; extra == "docs"
Provides-Extra: dev
Requires-Dist: spharpy[deploy,docs,tests]; extra == "dev"
